asf_enumeration/__init__.py
asf_enumeration/aria_s1_gunw.py
asf_enumeration/frame_maps/aria_frames.geojson
asf_enumeration-0.4.0.dist-info/licenses/LICENSE
asf_enumeration-0.4.0.dist-info/METADATA
asf_enumeration-0.4.0.dist-info/WHEEL
asf_enumeration-0.4.0.dist-info/top_level.txt
asf_enumeration-0.4.0.dist-info/RECORD
