Metadata-Version: 2.4
Name: asf_enumeration
Version: 0.4.0
Summary: Python library for enumerating ASF product inputs
Author-email: ASF APD/Tools Team <uaf-asf-apd@alaska.edu>
License-Expression: BSD-3-Clause
Project-URL: Homepage, https://github.com/ASFHyP3/asf-enumeration
Project-URL: Bug Tracker, https://github.com/ASFHyP3/asf-enumeration/issues
Classifier: Intended Audience :: Science/Research
Classifier: Natural Language :: English
Classifier: Operating System :: OS Independent
Classifier: Programming Language :: Python :: 3
Classifier: Programming Language :: Python :: 3.10
Classifier: Programming Language :: Python :: 3.11
Classifier: Programming Language :: Python :: 3.12
Classifier: Programming Language :: Python :: 3.13
Requires-Python: >=3.10
License-File: LICENSE
Requires-Dist: asf_search
Requires-Dist: requests
Requires-Dist: shapely
Provides-Extra: develop
Requires-Dist: pytest; extra == "develop"
Requires-Dist: pytest-cov; extra == "develop"
Dynamic: license-file
